py_time_between-0.1.2.dist-info/METADATA
py_time_between-0.1.2.dist-info/RECORD
py_time_between-0.1.2.dist-info/WHEEL
py_time_between-0.1.2.dist-info/top_level.txt
tests/__init__.py
tests/test_time_between.py
timebetween/__init__.py
