Metadata-Version: 2.1
Name: py-time-between
Version: 0.1.2
Summary: Ordinary package to say if a time variable falls between two given times.
Home-page: https://github.com/MicroarrayTecnologia/py-time-between
Author: Allan Silva
Author-email: allan.tavares@allantavares.com.br
License: UNKNOWN
Platform: UNKNOWN
Classifier: Programming Language :: Python :: 3
